<?xml version="1.0" encoding="utf-8" standalone="yes"?>
<Gesture Name = "^">
	<Stroke>
		<Point X = "-0.5060005" Y = "0.2401772" T = "0" Pressure = "0" />
		<Point X = "-0.4914352" Y = "0.2168711" T = "0" Pressure = "0" />
		<Point X = "-0.4768698" Y = "0.193565" T = "0" Pressure = "0" />
		<Point X = "-0.4617927" Y = "0.1705916" T = "0" Pressure = "0" />
		<Point X = "-0.4464074" Y = "0.1478184" T = "0" Pressure = "0" />
		<Point X = "-0.4310221" Y = "0.1250453" T = "0" Pressure = "0" />
		<Point X = "-0.4156367" Y = "0.1022722" T = "0" Pressure = "0" />
		<Point X = "-0.4002514" Y = "0.0794991" T = "0" Pressure = "0" />
		<Point X = "-0.3848681" Y = "0.05672473" T = "0" Pressure = "0" />
		<Point X = "-0.3703004" Y = "0.03342009" T = "0" Pressure = "0" />
		<Point X = "-0.3557328" Y = "0.01011544" T = "0" Pressure = "0" />
		<Point X = "-0.3411651" Y = "-0.01318921" T = "0" Pressure = "0" />
		<Point X = "-0.3265975" Y = "-0.03649386" T = "0" Pressure = "0" />
		<Point X = "-0.3120298" Y = "-0.05979851" T = "0" Pressure = "0" />
		<Point X = "-0.2974622" Y = "-0.08310315" T = "0" Pressure = "0" />
		<Point X = "-0.2828946" Y = "-0.1064078" T = "0" Pressure = "0" />
		<Point X = "-0.2683295" Y = "-0.1297141" T = "0" Pressure = "0" />
		<Point X = "-0.2537649" Y = "-0.1530206" T = "0" Pressure = "0" />
		<Point X = "-0.2392002" Y = "-0.1763271" T = "0" Pressure = "0" />
		<Point X = "-0.2246356" Y = "-0.1996336" T = "0" Pressure = "0" />
		<Point X = "-0.2100709" Y = "-0.2229401" T = "0" Pressure = "0" />
		<Point X = "-0.1955063" Y = "-0.2462467" T = "0" Pressure = "0" />
		<Point X = "-0.1809416" Y = "-0.2695532" T = "0" Pressure = "0" />
		<Point X = "-0.1660184" Y = "-0.2926304" T = "0" Pressure = "0" />
		<Point X = "-0.1509752" Y = "-0.315631" T = "0" Pressure = "0" />
		<Point X = "-0.1359321" Y = "-0.3386315" T = "0" Pressure = "0" />
		<Point X = "-0.1208889" Y = "-0.3616321" T = "0" Pressure = "0" />
		<Point X = "-0.1052171" Y = "-0.3826532" T = "0" Pressure = "0" />
		<Point X = "-0.09068413" Y = "-0.3617035" T = "0" Pressure = "0" />
		<Point X = "-0.0783511" Y = "-0.3371433" T = "0" Pressure = "0" />
		<Point X = "-0.06578" Y = "-0.3127038" T = "0" Pressure = "0" />
		<Point X = "-0.05320889" Y = "-0.2882642" T = "0" Pressure = "0" />
		<Point X = "-0.04063779" Y = "-0.2638247" T = "0" Pressure = "0" />
		<Point X = "-0.02806668" Y = "-0.2393852" T = "0" Pressure = "0" />
		<Point X = "-0.01513856" Y = "-0.2151458" T = "0" Pressure = "0" />
		<Point X = "-0.0008486195" Y = "-0.1916699" T = "0" Pressure = "0" />
		<Point X = "0.01344132" Y = "-0.1681939" T = "0" Pressure = "0" />
		<Point X = "0.02773126" Y = "-0.144718" T = "0" Pressure = "0" />
		<Point X = "0.04202121" Y = "-0.121242" T = "0" Pressure = "0" />
		<Point X = "0.05631115" Y = "-0.09776606" T = "0" Pressure = "0" />
		<Point X = "0.07060109" Y = "-0.0742901" T = "0" Pressure = "0" />
		<Point X = "0.08519295" Y = "-0.05100427" T = "0" Pressure = "0" />
		<Point X = "0.1001888" Y = "-0.02797282" T = "0" Pressure = "0" />
		<Point X = "0.1151846" Y = "-0.004941382" T = "0" Pressure = "0" />
		<Point X = "0.1301805" Y = "0.01809006" T = "0" Pressure = "0" />
		<Point X = "0.1451763" Y = "0.04112151" T = "0" Pressure = "0" />
		<Point X = "0.1601722" Y = "0.06415295" T = "0" Pressure = "0" />
		<Point X = "0.175168" Y = "0.08718439" T = "0" Pressure = "0" />
		<Point X = "0.1931653" Y = "0.1079438" T = "0" Pressure = "0" />
		<Point X = "0.2112616" Y = "0.1286282" T = "0" Pressure = "0" />
		<Point X = "0.229358" Y = "0.1493127" T = "0" Pressure = "0" />
		<Point X = "0.2474543" Y = "0.1699971" T = "0" Pressure = "0" />
		<Point X = "0.2655506" Y = "0.1906815" T = "0" Pressure = "0" />
		<Point X = "0.2839148" Y = "0.2111265" T = "0" Pressure = "0" />
		<Point X = "0.3024472" Y = "0.2314211" T = "0" Pressure = "0" />
		<Point X = "0.3209797" Y = "0.2517157" T = "0" Pressure = "0" />
		<Point X = "0.3395122" Y = "0.2720103" T = "0" Pressure = "0" />
		<Point X = "0.3600747" Y = "0.2901375" T = "0" Pressure = "0" />
		<Point X = "0.3815376" Y = "0.3073033" T = "0" Pressure = "0" />
		<Point X = "0.4030006" Y = "0.3244691" T = "0" Pressure = "0" />
		<Point X = "0.4247894" Y = "0.3412096" T = "0" Pressure = "0" />
		<Point X = "0.4469485" Y = "0.3574668" T = "0" Pressure = "0" />
		<Point X = "0.4694144" Y = "0.3732216" T = "0" Pressure = "0" />
		<Point X = "0.4939993" Y = "0.3855059" T = "0" Pressure = "0" />
	</Stroke>
</Gesture>
