<?xml version="1.0" encoding="utf-8" standalone="yes"?>
<Gesture Name = "J">
	<Stroke>
		<Point X = "-0.1518225" Y = "-0.5209669" T = "0" Pressure = "0" />
		<Point X = "-0.1314997" Y = "-0.5209669" T = "0" Pressure = "0" />
		<Point X = "-0.1111768" Y = "-0.5209669" T = "0" Pressure = "0" />
		<Point X = "-0.090854" Y = "-0.5209669" T = "0" Pressure = "0" />
		<Point X = "-0.07053117" Y = "-0.5209669" T = "0" Pressure = "0" />
		<Point X = "-0.05020834" Y = "-0.5209669" T = "0" Pressure = "0" />
		<Point X = "-0.02988551" Y = "-0.5209669" T = "0" Pressure = "0" />
		<Point X = "-0.009562675" Y = "-0.5209669" T = "0" Pressure = "0" />
		<Point X = "0.01076015" Y = "-0.5209669" T = "0" Pressure = "0" />
		<Point X = "0.03108298" Y = "-0.5209669" T = "0" Pressure = "0" />
		<Point X = "0.05140582" Y = "-0.5209669" T = "0" Pressure = "0" />
		<Point X = "0.07172865" Y = "-0.5209669" T = "0" Pressure = "0" />
		<Point X = "0.09205148" Y = "-0.5209669" T = "0" Pressure = "0" />
		<Point X = "0.1123743" Y = "-0.5209669" T = "0" Pressure = "0" />
		<Point X = "0.1326971" Y = "-0.5209669" T = "0" Pressure = "0" />
		<Point X = "0.15302" Y = "-0.5209669" T = "0" Pressure = "0" />
		<Point X = "0.1733428" Y = "-0.5209669" T = "0" Pressure = "0" />
		<Point X = "0.1936656" Y = "-0.5209669" T = "0" Pressure = "0" />
		<Point X = "0.2139885" Y = "-0.5209669" T = "0" Pressure = "0" />
		<Point X = "0.2343113" Y = "-0.5209669" T = "0" Pressure = "0" />
		<Point X = "0.2546341" Y = "-0.5209669" T = "0" Pressure = "0" />
		<Point X = "0.274957" Y = "-0.5209669" T = "0" Pressure = "0" />
		<Point X = "0.2952798" Y = "-0.5209669" T = "0" Pressure = "0" />
		<Point X = "0.3156026" Y = "-0.5209669" T = "0" Pressure = "0" />
		<Point X = "0.3359255" Y = "-0.5209669" T = "0" Pressure = "0" />
		<Point X = "0.3562483" Y = "-0.5209669" T = "0" Pressure = "0" />
		<Point X = "0.3765711" Y = "-0.5209669" T = "0" Pressure = "0" />
		<Point X = "0.3968939" Y = "-0.5209669" T = "0" Pressure = "0" />
	</Stroke>
	<Stroke>
		<Point X = "0.03739011" Y = "-0.4637436" T = "0" Pressure = "0" />
		<Point X = "0.03739011" Y = "-0.4434208" T = "0" Pressure = "0" />
		<Point X = "0.03739011" Y = "-0.423098" T = "0" Pressure = "0" />
		<Point X = "0.03739011" Y = "-0.4027751" T = "0" Pressure = "0" />
		<Point X = "0.03739011" Y = "-0.3824523" T = "0" Pressure = "0" />
		<Point X = "0.03739011" Y = "-0.3621294" T = "0" Pressure = "0" />
		<Point X = "0.03857195" Y = "-0.3418473" T = "0" Pressure = "0" />
		<Point X = "0.0399683" Y = "-0.3215725" T = "0" Pressure = "0" />
		<Point X = "0.04136466" Y = "-0.3012977" T = "0" Pressure = "0" />
		<Point X = "0.0427537" Y = "-0.2810224" T = "0" Pressure = "0" />
		<Point X = "0.04410697" Y = "-0.2607446" T = "0" Pressure = "0" />
		<Point X = "0.04546024" Y = "-0.2404669" T = "0" Pressure = "0" />
		<Point X = "0.04681351" Y = "-0.2201892" T = "0" Pressure = "0" />
		<Point X = "0.04827236" Y = "-0.1999193" T = "0" Pressure = "0" />
		<Point X = "0.04991376" Y = "-0.1796628" T = "0" Pressure = "0" />
		<Point X = "0.05155516" Y = "-0.1594064" T = "0" Pressure = "0" />
		<Point X = "0.05319656" Y = "-0.13915" T = "0" Pressure = "0" />
		<Point X = "0.05483796" Y = "-0.1188935" T = "0" Pressure = "0" />
		<Point X = "0.05537811" Y = "-0.09859254" T = "0" Pressure = "0" />
		<Point X = "0.05537811" Y = "-0.07826971" T = "0" Pressure = "0" />
		<Point X = "0.05537811" Y = "-0.05794688" T = "0" Pressure = "0" />
		<Point X = "0.05537811" Y = "-0.03762405" T = "0" Pressure = "0" />
		<Point X = "0.05481189" Y = "-0.01731388" T = "0" Pressure = "0" />
		<Point X = "0.05390342" Y = "0.002988636" T = "0" Pressure = "0" />
		<Point X = "0.05299494" Y = "0.02329115" T = "0" Pressure = "0" />
		<Point X = "0.05208647" Y = "0.04359367" T = "0" Pressure = "0" />
		<Point X = "0.051178" Y = "0.06389619" T = "0" Pressure = "0" />
		<Point X = "0.05026953" Y = "0.0841987" T = "0" Pressure = "0" />
		<Point X = "0.04936106" Y = "0.1045012" T = "0" Pressure = "0" />
		<Point X = "0.04845259" Y = "0.1248037" T = "0" Pressure = "0" />
		<Point X = "0.0474355" Y = "0.1450993" T = "0" Pressure = "0" />
		<Point X = "0.04574876" Y = "0.165352" T = "0" Pressure = "0" />
		<Point X = "0.04406202" Y = "0.1856047" T = "0" Pressure = "0" />
		<Point X = "0.04237528" Y = "0.2058574" T = "0" Pressure = "0" />
		<Point X = "0.04068854" Y = "0.2261101" T = "0" Pressure = "0" />
		<Point X = "0.03860988" Y = "0.2463235" T = "0" Pressure = "0" />
		<Point X = "0.03623588" Y = "0.2665072" T = "0" Pressure = "0" />
		<Point X = "0.03386189" Y = "0.2866909" T = "0" Pressure = "0" />
		<Point X = "0.03148789" Y = "0.3068746" T = "0" Pressure = "0" />
		<Point X = "0.02912389" Y = "0.3270594" T = "0" Pressure = "0" />
		<Point X = "0.02679161" Y = "0.347248" T = "0" Pressure = "0" />
		<Point X = "0.02445933" Y = "0.3674366" T = "0" Pressure = "0" />
		<Point X = "0.02212705" Y = "0.3876251" T = "0" Pressure = "0" />
		<Point X = "0.01987956" Y = "0.4078233" T = "0" Pressure = "0" />
		<Point X = "0.01763852" Y = "0.4280222" T = "0" Pressure = "0" />
		<Point X = "0.01309589" Y = "0.4477518" T = "0" Pressure = "0" />
		<Point X = "0.006223073" Y = "0.4668086" T = "0" Pressure = "0" />
		<Point X = "-0.00813354" Y = "0.4764594" T = "0" Pressure = "0" />
		<Point X = "-0.02845637" Y = "0.4764594" T = "0" Pressure = "0" />
		<Point X = "-0.04872141" Y = "0.4757897" T = "0" Pressure = "0" />
		<Point X = "-0.0687438" Y = "0.4723081" T = "0" Pressure = "0" />
		<Point X = "-0.08876619" Y = "0.4688266" T = "0" Pressure = "0" />
		<Point X = "-0.1086686" Y = "0.4648254" T = "0" Pressure = "0" />
		<Point X = "-0.1281897" Y = "0.4591737" T = "0" Pressure = "0" />
		<Point X = "-0.1477109" Y = "0.453522" T = "0" Pressure = "0" />
		<Point X = "-0.1672321" Y = "0.4478703" T = "0" Pressure = "0" />
		<Point X = "-0.1867532" Y = "0.4422185" T = "0" Pressure = "0" />
		<Point X = "-0.2061443" Y = "0.4361802" T = "0" Pressure = "0" />
		<Point X = "-0.2251126" Y = "0.428885" T = "0" Pressure = "0" />
		<Point X = "-0.244081" Y = "0.4215898" T = "0" Pressure = "0" />
		<Point X = "-0.2630493" Y = "0.4142946" T = "0" Pressure = "0" />
		<Point X = "-0.2811618" Y = "0.4051679" T = "0" Pressure = "0" />
		<Point X = "-0.2989266" Y = "0.3952974" T = "0" Pressure = "0" />
		<Point X = "-0.3164896" Y = "0.385126" T = "0" Pressure = "0" />
		<Point X = "-0.3323607" Y = "0.3724324" T = "0" Pressure = "0" />
		<Point X = "-0.3455935" Y = "0.3574335" T = "0" Pressure = "0" />
		<Point X = "-0.3559213" Y = "0.3399696" T = "0" Pressure = "0" />
		<Point X = "-0.3559213" Y = "0.3196469" T = "0" Pressure = "0" />
	</Stroke>
</Gesture>
