<?xml version="1.0" encoding="utf-8" standalone="yes"?>
<Gesture Name = "J">
	<Stroke>
		<Point X = "-0.2008108" Y = "-0.5335723" T = "0" Pressure = "0" />
		<Point X = "-0.1812762" Y = "-0.5335723" T = "0" Pressure = "0" />
		<Point X = "-0.1617416" Y = "-0.5335723" T = "0" Pressure = "0" />
		<Point X = "-0.1422071" Y = "-0.5335723" T = "0" Pressure = "0" />
		<Point X = "-0.1226725" Y = "-0.5335723" T = "0" Pressure = "0" />
		<Point X = "-0.1031781" Y = "-0.5324442" T = "0" Pressure = "0" />
		<Point X = "-0.08369304" Y = "-0.5310546" T = "0" Pressure = "0" />
		<Point X = "-0.06420797" Y = "-0.5296649" T = "0" Pressure = "0" />
		<Point X = "-0.04471269" Y = "-0.5287644" T = "0" Pressure = "0" />
		<Point X = "-0.02518659" Y = "-0.5293394" T = "0" Pressure = "0" />
		<Point X = "-0.005660489" Y = "-0.5299144" T = "0" Pressure = "0" />
		<Point X = "0.01386561" Y = "-0.5304894" T = "0" Pressure = "0" />
		<Point X = "0.03339171" Y = "-0.5310644" T = "0" Pressure = "0" />
		<Point X = "0.05290515" Y = "-0.5319683" T = "0" Pressure = "0" />
		<Point X = "0.07241767" Y = "-0.5328961" T = "0" Pressure = "0" />
		<Point X = "0.09193019" Y = "-0.5338238" T = "0" Pressure = "0" />
		<Point X = "0.1114427" Y = "-0.5347517" T = "0" Pressure = "0" />
		<Point X = "0.1309552" Y = "-0.5356794" T = "0" Pressure = "0" />
		<Point X = "0.1504202" Y = "-0.5372417" T = "0" Pressure = "0" />
		<Point X = "0.1698528" Y = "-0.5392343" T = "0" Pressure = "0" />
		<Point X = "0.1892855" Y = "-0.5412269" T = "0" Pressure = "0" />
		<Point X = "0.2087182" Y = "-0.5432196" T = "0" Pressure = "0" />
		<Point X = "0.2281508" Y = "-0.5452121" T = "0" Pressure = "0" />
		<Point X = "0.2475059" Y = "-0.5478107" T = "0" Pressure = "0" />
		<Point X = "0.2668134" Y = "-0.5507808" T = "0" Pressure = "0" />
		<Point X = "0.2861208" Y = "-0.5537509" T = "0" Pressure = "0" />
	</Stroke>
	<Stroke>
		<Point X = "0.05109325" Y = "-0.5371258" T = "0" Pressure = "0" />
		<Point X = "0.05109325" Y = "-0.5175912" T = "0" Pressure = "0" />
		<Point X = "0.0518691" Y = "-0.4980769" T = "0" Pressure = "0" />
		<Point X = "0.05289155" Y = "-0.4785691" T = "0" Pressure = "0" />
		<Point X = "0.05412096" Y = "-0.4590754" T = "0" Pressure = "0" />
		<Point X = "0.05574499" Y = "-0.4396085" T = "0" Pressure = "0" />
		<Point X = "0.05736901" Y = "-0.4201415" T = "0" Pressure = "0" />
		<Point X = "0.05895741" Y = "-0.4006718" T = "0" Pressure = "0" />
		<Point X = "0.06045746" Y = "-0.3811949" T = "0" Pressure = "0" />
		<Point X = "0.0619575" Y = "-0.361718" T = "0" Pressure = "0" />
		<Point X = "0.06345755" Y = "-0.3422411" T = "0" Pressure = "0" />
		<Point X = "0.06468051" Y = "-0.3227449" T = "0" Pressure = "0" />
		<Point X = "0.06589724" Y = "-0.3032483" T = "0" Pressure = "0" />
		<Point X = "0.06711397" Y = "-0.2837516" T = "0" Pressure = "0" />
		<Point X = "0.0683307" Y = "-0.264255" T = "0" Pressure = "0" />
		<Point X = "0.0684416" Y = "-0.2447239" T = "0" Pressure = "0" />
		<Point X = "0.0684416" Y = "-0.2251893" T = "0" Pressure = "0" />
		<Point X = "0.0684416" Y = "-0.2056548" T = "0" Pressure = "0" />
		<Point X = "0.0684416" Y = "-0.1861202" T = "0" Pressure = "0" />
		<Point X = "0.0684416" Y = "-0.1665856" T = "0" Pressure = "0" />
		<Point X = "0.0684416" Y = "-0.1470511" T = "0" Pressure = "0" />
		<Point X = "0.0684416" Y = "-0.1275165" T = "0" Pressure = "0" />
		<Point X = "0.0684416" Y = "-0.1079819" T = "0" Pressure = "0" />
		<Point X = "0.0684416" Y = "-0.08844738" T = "0" Pressure = "0" />
		<Point X = "0.0684416" Y = "-0.06891281" T = "0" Pressure = "0" />
		<Point X = "0.0684416" Y = "-0.04937824" T = "0" Pressure = "0" />
		<Point X = "0.06961049" Y = "-0.02989104" T = "0" Pressure = "0" />
		<Point X = "0.07119098" Y = "-0.01042052" T = "0" Pressure = "0" />
		<Point X = "0.07277147" Y = "0.009050002" T = "0" Pressure = "0" />
		<Point X = "0.07435197" Y = "0.02852053" T = "0" Pressure = "0" />
		<Point X = "0.07591678" Y = "0.0479921" T = "0" Pressure = "0" />
		<Point X = "0.07694207" Y = "0.06749973" T = "0" Pressure = "0" />
		<Point X = "0.07796736" Y = "0.08700737" T = "0" Pressure = "0" />
		<Point X = "0.07899265" Y = "0.106515" T = "0" Pressure = "0" />
		<Point X = "0.08001795" Y = "0.1260227" T = "0" Pressure = "0" />
		<Point X = "0.08096874" Y = "0.1455335" T = "0" Pressure = "0" />
		<Point X = "0.08162022" Y = "0.1650572" T = "0" Pressure = "0" />
		<Point X = "0.0822717" Y = "0.1845809" T = "0" Pressure = "0" />
		<Point X = "0.08292317" Y = "0.2041046" T = "0" Pressure = "0" />
		<Point X = "0.08407667" Y = "0.2235949" T = "0" Pressure = "0" />
		<Point X = "0.08601738" Y = "0.2430328" T = "0" Pressure = "0" />
		<Point X = "0.08795809" Y = "0.2624708" T = "0" Pressure = "0" />
		<Point X = "0.08827204" Y = "0.2819897" T = "0" Pressure = "0" />
		<Point X = "0.08827204" Y = "0.3015242" T = "0" Pressure = "0" />
		<Point X = "0.08827204" Y = "0.3210588" T = "0" Pressure = "0" />
		<Point X = "0.08604778" Y = "0.3404551" T = "0" Pressure = "0" />
		<Point X = "0.08362797" Y = "0.3598392" T = "0" Pressure = "0" />
		<Point X = "0.08201123" Y = "0.3793043" T = "0" Pressure = "0" />
		<Point X = "0.07980575" Y = "0.3986668" T = "0" Pressure = "0" />
		<Point X = "0.07416271" Y = "0.4172418" T = "0" Pressure = "0" />
		<Point X = "0.06019586" Y = "0.4278632" T = "0" Pressure = "0" />
		<Point X = "0.04138564" Y = "0.4329232" T = "0" Pressure = "0" />
		<Point X = "0.02211731" Y = "0.4361374" T = "0" Pressure = "0" />
		<Point X = "0.002848366" Y = "0.4393478" T = "0" Pressure = "0" />
		<Point X = "-0.01642071" Y = "0.4425575" T = "0" Pressure = "0" />
		<Point X = "-0.03582643" Y = "0.4441152" T = "0" Pressure = "0" />
		<Point X = "-0.05536099" Y = "0.4441152" T = "0" Pressure = "0" />
		<Point X = "-0.07489555" Y = "0.4441152" T = "0" Pressure = "0" />
		<Point X = "-0.09443012" Y = "0.4441152" T = "0" Pressure = "0" />
		<Point X = "-0.1136052" Y = "0.4424784" T = "0" Pressure = "0" />
		<Point X = "-0.1313421" Y = "0.4342929" T = "0" Pressure = "0" />
		<Point X = "-0.149079" Y = "0.4261074" T = "0" Pressure = "0" />
		<Point X = "-0.1668158" Y = "0.4179219" T = "0" Pressure = "0" />
		<Point X = "-0.1845527" Y = "0.4097364" T = "0" Pressure = "0" />
		<Point X = "-0.2022896" Y = "0.4015509" T = "0" Pressure = "0" />
		<Point X = "-0.2187296" Y = "0.3911084" T = "0" Pressure = "0" />
		<Point X = "-0.2347333" Y = "0.3799067" T = "0" Pressure = "0" />
		<Point X = "-0.2507371" Y = "0.3687049" T = "0" Pressure = "0" />
		<Point X = "-0.2664949" Y = "0.3571638" T = "0" Pressure = "0" />
		<Point X = "-0.2786563" Y = "0.34495" T = "0" Pressure = "0" />
	</Stroke>
</Gesture>
