<?xml version="1.0" encoding="utf-8" standalone="yes"?>
<Gesture Name = "K">
	<Stroke>
		<Point X = "-0.1345169" Y = "-0.5740726" T = "0" Pressure = "0" />
		<Point X = "-0.1365937" Y = "-0.5491835" T = "0" Pressure = "0" />
		<Point X = "-0.1386705" Y = "-0.5242945" T = "0" Pressure = "0" />
		<Point X = "-0.1404991" Y = "-0.4993868" T = "0" Pressure = "0" />
		<Point X = "-0.1421593" Y = "-0.4744665" T = "0" Pressure = "0" />
		<Point X = "-0.1438195" Y = "-0.4495462" T = "0" Pressure = "0" />
		<Point X = "-0.1454797" Y = "-0.4246259" T = "0" Pressure = "0" />
		<Point X = "-0.1471509" Y = "-0.3997064" T = "0" Pressure = "0" />
		<Point X = "-0.14893" Y = "-0.3747943" T = "0" Pressure = "0" />
		<Point X = "-0.1507091" Y = "-0.3498822" T = "0" Pressure = "0" />
		<Point X = "-0.1524882" Y = "-0.3249701" T = "0" Pressure = "0" />
		<Point X = "-0.1542673" Y = "-0.300058" T = "0" Pressure = "0" />
		<Point X = "-0.1560464" Y = "-0.2751459" T = "0" Pressure = "0" />
		<Point X = "-0.1577298" Y = "-0.2502273" T = "0" Pressure = "0" />
		<Point X = "-0.1593121" Y = "-0.2253019" T = "0" Pressure = "0" />
		<Point X = "-0.1608944" Y = "-0.2003766" T = "0" Pressure = "0" />
		<Point X = "-0.1624767" Y = "-0.1754512" T = "0" Pressure = "0" />
		<Point X = "-0.1640591" Y = "-0.1505258" T = "0" Pressure = "0" />
		<Point X = "-0.1656414" Y = "-0.1256005" T = "0" Pressure = "0" />
		<Point X = "-0.1672718" Y = "-0.1006784" T = "0" Pressure = "0" />
		<Point X = "-0.1691164" Y = "-0.07577106" T = "0" Pressure = "0" />
		<Point X = "-0.1709609" Y = "-0.05086372" T = "0" Pressure = "0" />
		<Point X = "-0.1728055" Y = "-0.02595638" T = "0" Pressure = "0" />
		<Point X = "-0.17465" Y = "-0.001049037" T = "0" Pressure = "0" />
		<Point X = "-0.1764945" Y = "0.0238583" T = "0" Pressure = "0" />
		<Point X = "-0.1789587" Y = "0.04870975" T = "0" Pressure = "0" />
		<Point X = "-0.1816013" Y = "0.07354511" T = "0" Pressure = "0" />
		<Point X = "-0.1842438" Y = "0.09838046" T = "0" Pressure = "0" />
		<Point X = "-0.1868863" Y = "0.1232158" T = "0" Pressure = "0" />
		<Point X = "-0.1895416" Y = "0.1480498" T = "0" Pressure = "0" />
		<Point X = "-0.192405" Y = "0.1728606" T = "0" Pressure = "0" />
		<Point X = "-0.1952685" Y = "0.1976715" T = "0" Pressure = "0" />
		<Point X = "-0.198132" Y = "0.2224823" T = "0" Pressure = "0" />
		<Point X = "-0.2009954" Y = "0.2472932" T = "0" Pressure = "0" />
		<Point X = "-0.2038589" Y = "0.272104" T = "0" Pressure = "0" />
		<Point X = "-0.2063406" Y = "0.2969554" T = "0" Pressure = "0" />
		<Point X = "-0.2087446" Y = "0.321815" T = "0" Pressure = "0" />
		<Point X = "-0.2111486" Y = "0.3466745" T = "0" Pressure = "0" />
		<Point X = "-0.2136135" Y = "0.3715281" T = "0" Pressure = "0" />
		<Point X = "-0.2161018" Y = "0.3963794" T = "0" Pressure = "0" />
		<Point X = "-0.2168133" Y = "0.4213194" T = "0" Pressure = "0" />
	</Stroke>
	<Stroke>
		<Point X = "0.4296856" Y = "-0.414397" T = "0" Pressure = "0" />
		<Point X = "0.4110188" Y = "-0.3978039" T = "0" Pressure = "0" />
		<Point X = "0.392352" Y = "-0.3812109" T = "0" Pressure = "0" />
		<Point X = "0.3736852" Y = "-0.3646179" T = "0" Pressure = "0" />
		<Point X = "0.3550072" Y = "-0.3480389" T = "0" Pressure = "0" />
		<Point X = "0.3345628" Y = "-0.3336931" T = "0" Pressure = "0" />
		<Point X = "0.3141184" Y = "-0.3193472" T = "0" Pressure = "0" />
		<Point X = "0.293674" Y = "-0.3050014" T = "0" Pressure = "0" />
		<Point X = "0.2732295" Y = "-0.2906555" T = "0" Pressure = "0" />
		<Point X = "0.2527851" Y = "-0.2763096" T = "0" Pressure = "0" />
		<Point X = "0.2323407" Y = "-0.2619638" T = "0" Pressure = "0" />
		<Point X = "0.2118784" Y = "-0.2476441" T = "0" Pressure = "0" />
		<Point X = "0.1910985" Y = "-0.2337887" T = "0" Pressure = "0" />
		<Point X = "0.1703185" Y = "-0.2199334" T = "0" Pressure = "0" />
		<Point X = "0.1495385" Y = "-0.206078" T = "0" Pressure = "0" />
		<Point X = "0.1287585" Y = "-0.1922227" T = "0" Pressure = "0" />
		<Point X = "0.1079786" Y = "-0.1783673" T = "0" Pressure = "0" />
		<Point X = "0.08719859" Y = "-0.164512" T = "0" Pressure = "0" />
		<Point X = "0.0663382" Y = "-0.1507786" T = "0" Pressure = "0" />
		<Point X = "0.04541789" Y = "-0.1371361" T = "0" Pressure = "0" />
		<Point X = "0.02449758" Y = "-0.1234935" T = "0" Pressure = "0" />
		<Point X = "0.003577275" Y = "-0.109851" T = "0" Pressure = "0" />
		<Point X = "-0.01734303" Y = "-0.09620846" T = "0" Pressure = "0" />
		<Point X = "-0.03841383" Y = "-0.08283568" T = "0" Pressure = "0" />
		<Point X = "-0.06101178" Y = "-0.07220033" T = "0" Pressure = "0" />
		<Point X = "-0.08360972" Y = "-0.06156497" T = "0" Pressure = "0" />
		<Point X = "-0.1062077" Y = "-0.05092961" T = "0" Pressure = "0" />
		<Point X = "-0.1286379" Y = "-0.03995766" T = "0" Pressure = "0" />
		<Point X = "-0.150739" Y = "-0.02832489" T = "0" Pressure = "0" />
		<Point X = "-0.1719806" Y = "-0.0155256" T = "0" Pressure = "0" />
		<Point X = "-0.1564827" Y = "0.0001398739" T = "0" Pressure = "0" />
		<Point X = "-0.1353031" Y = "0.01337626" T = "0" Pressure = "0" />
		<Point X = "-0.1129551" Y = "0.0244616" T = "0" Pressure = "0" />
		<Point X = "-0.09032235" Y = "0.03502274" T = "0" Pressure = "0" />
		<Point X = "-0.06768962" Y = "0.04558388" T = "0" Pressure = "0" />
		<Point X = "-0.04525541" Y = "0.05655101" T = "0" Pressure = "0" />
		<Point X = "-0.0230211" Y = "0.06792703" T = "0" Pressure = "0" />
		<Point X = "-0.0007868001" Y = "0.07930303" T = "0" Pressure = "0" />
		<Point X = "0.0214475" Y = "0.09067905" T = "0" Pressure = "0" />
		<Point X = "0.04368181" Y = "0.1020551" T = "0" Pressure = "0" />
		<Point X = "0.06612318" Y = "0.1130122" T = "0" Pressure = "0" />
		<Point X = "0.08866388" Y = "0.1237683" T = "0" Pressure = "0" />
		<Point X = "0.1112046" Y = "0.1345245" T = "0" Pressure = "0" />
		<Point X = "0.1337453" Y = "0.1452806" T = "0" Pressure = "0" />
		<Point X = "0.156286" Y = "0.1560368" T = "0" Pressure = "0" />
		<Point X = "0.1784191" Y = "0.1675999" T = "0" Pressure = "0" />
		<Point X = "0.2004552" Y = "0.1793553" T = "0" Pressure = "0" />
		<Point X = "0.2224913" Y = "0.1911107" T = "0" Pressure = "0" />
		<Point X = "0.2440867" Y = "0.2036144" T = "0" Pressure = "0" />
		<Point X = "0.2650556" Y = "0.2171821" T = "0" Pressure = "0" />
		<Point X = "0.285329" Y = "0.2316949" T = "0" Pressure = "0" />
		<Point X = "0.3045179" Y = "0.2476813" T = "0" Pressure = "0" />
		<Point X = "0.3238254" Y = "0.2635239" T = "0" Pressure = "0" />
		<Point X = "0.3424682" Y = "0.2800987" T = "0" Pressure = "0" />
		<Point X = "0.3601285" Y = "0.297759" T = "0" Pressure = "0" />
	</Stroke>
</Gesture>
