<?xml version="1.0" encoding="utf-8" standalone="yes"?>
<Gesture Name = "S">
	<Stroke>
		<Point X = "0.2837822" Y = "-0.3654193" T = "0" Pressure = "0" />
		<Point X = "0.2837822" Y = "-0.3885814" T = "0" Pressure = "0" />
		<Point X = "0.2756531" Y = "-0.4100997" T = "0" Pressure = "0" />
		<Point X = "0.2606895" Y = "-0.4277794" T = "0" Pressure = "0" />
		<Point X = "0.2441991" Y = "-0.4439575" T = "0" Pressure = "0" />
		<Point X = "0.2267692" Y = "-0.4592115" T = "0" Pressure = "0" />
		<Point X = "0.2072553" Y = "-0.4716054" T = "0" Pressure = "0" />
		<Point X = "0.1873948" Y = "-0.4835238" T = "0" Pressure = "0" />
		<Point X = "0.1664001" Y = "-0.4932819" T = "0" Pressure = "0" />
		<Point X = "0.1453127" Y = "-0.5028634" T = "0" Pressure = "0" />
		<Point X = "0.1242271" Y = "-0.5124488" T = "0" Pressure = "0" />
		<Point X = "0.1031415" Y = "-0.5220345" T = "0" Pressure = "0" />
		<Point X = "0.08061911" Y = "-0.5272679" T = "0" Pressure = "0" />
		<Point X = "0.05797107" Y = "-0.5321209" T = "0" Pressure = "0" />
		<Point X = "0.03532302" Y = "-0.5369738" T = "0" Pressure = "0" />
		<Point X = "0.01254096" Y = "-0.5410012" T = "0" Pressure = "0" />
		<Point X = "-0.01047918" Y = "-0.543562" T = "0" Pressure = "0" />
		<Point X = "-0.03362136" Y = "-0.5439221" T = "0" Pressure = "0" />
		<Point X = "-0.05635757" Y = "-0.540461" T = "0" Pressure = "0" />
		<Point X = "-0.07865306" Y = "-0.5342713" T = "0" Pressure = "0" />
		<Point X = "-0.1003463" Y = "-0.5261609" T = "0" Pressure = "0" />
		<Point X = "-0.1211613" Y = "-0.5161851" T = "0" Pressure = "0" />
		<Point X = "-0.1408328" Y = "-0.5039605" T = "0" Pressure = "0" />
		<Point X = "-0.1601075" Y = "-0.4911163" T = "0" Pressure = "0" />
		<Point X = "-0.1785322" Y = "-0.4770861" T = "0" Pressure = "0" />
		<Point X = "-0.1957677" Y = "-0.4616841" T = "0" Pressure = "0" />
		<Point X = "-0.2123437" Y = "-0.4455194" T = "0" Pressure = "0" />
		<Point X = "-0.2299278" Y = "-0.4304435" T = "0" Pressure = "0" />
		<Point X = "-0.2457648" Y = "-0.4136449" T = "0" Pressure = "0" />
		<Point X = "-0.2596805" Y = "-0.3951952" T = "0" Pressure = "0" />
		<Point X = "-0.2716342" Y = "-0.3753707" T = "0" Pressure = "0" />
		<Point X = "-0.2810531" Y = "-0.3542195" T = "0" Pressure = "0" />
		<Point X = "-0.288333" Y = "-0.3322329" T = "0" Pressure = "0" />
		<Point X = "-0.2939506" Y = "-0.3097623" T = "0" Pressure = "0" />
		<Point X = "-0.297759" Y = "-0.2869539" T = "0" Pressure = "0" />
		<Point X = "-0.3006907" Y = "-0.2639782" T = "0" Pressure = "0" />
		<Point X = "-0.3035477" Y = "-0.241006" T = "0" Pressure = "0" />
		<Point X = "-0.3035477" Y = "-0.2178439" T = "0" Pressure = "0" />
		<Point X = "-0.3035477" Y = "-0.1946817" T = "0" Pressure = "0" />
		<Point X = "-0.2982658" Y = "-0.1722592" T = "0" Pressure = "0" />
		<Point X = "-0.2916237" Y = "-0.150071" T = "0" Pressure = "0" />
		<Point X = "-0.282486" Y = "-0.1289411" T = "0" Pressure = "0" />
		<Point X = "-0.2707297" Y = "-0.1089967" T = "0" Pressure = "0" />
		<Point X = "-0.2576087" Y = "-0.08990943" T = "0" Pressure = "0" />
		<Point X = "-0.2438826" Y = "-0.07126483" T = "0" Pressure = "0" />
		<Point X = "-0.2296647" Y = "-0.05298002" T = "0" Pressure = "0" />
		<Point X = "-0.2130795" Y = "-0.03698391" T = "0" Pressure = "0" />
		<Point X = "-0.1952842" Y = "-0.02215791" T = "0" Pressure = "0" />
		<Point X = "-0.1766386" Y = "-0.008444116" T = "0" Pressure = "0" />
		<Point X = "-0.157663" Y = "0.004837832" T = "0" Pressure = "0" />
		<Point X = "-0.1371165" Y = "0.01531862" T = "0" Pressure = "0" />
		<Point X = "-0.1158877" Y = "0.02458258" T = "0" Pressure = "0" />
		<Point X = "-0.09465884" Y = "0.03384655" T = "0" Pressure = "0" />
		<Point X = "-0.07342999" Y = "0.04311051" T = "0" Pressure = "0" />
		<Point X = "-0.05220115" Y = "0.05237448" T = "0" Pressure = "0" />
		<Point X = "-0.03050276" Y = "0.06043882" T = "0" Pressure = "0" />
		<Point X = "-0.008625792" Y = "0.06804692" T = "0" Pressure = "0" />
		<Point X = "0.01346882" Y = "0.07498274" T = "0" Pressure = "0" />
		<Point X = "0.03565382" Y = "0.08163938" T = "0" Pressure = "0" />
		<Point X = "0.05696378" Y = "0.09070631" T = "0" Pressure = "0" />
		<Point X = "0.07723289" Y = "0.1018256" T = "0" Pressure = "0" />
		<Point X = "0.09709679" Y = "0.1137382" T = "0" Pressure = "0" />
		<Point X = "0.1155706" Y = "0.12765" T = "0" Pressure = "0" />
		<Point X = "0.1337995" Y = "0.1419389" T = "0" Pressure = "0" />
		<Point X = "0.1518053" Y = "0.1565066" T = "0" Pressure = "0" />
		<Point X = "0.1698278" Y = "0.171055" T = "0" Pressure = "0" />
		<Point X = "0.1863952" Y = "0.1871118" T = "0" Pressure = "0" />
		<Point X = "0.2023845" Y = "0.2038536" T = "0" Pressure = "0" />
		<Point X = "0.2169853" Y = "0.2217734" T = "0" Pressure = "0" />
		<Point X = "0.2272872" Y = "0.2424333" T = "0" Pressure = "0" />
		<Point X = "0.2342084" Y = "0.2645022" T = "0" Pressure = "0" />
		<Point X = "0.2358038" Y = "0.2875508" T = "0" Pressure = "0" />
		<Point X = "0.2358038" Y = "0.3107129" T = "0" Pressure = "0" />
		<Point X = "0.2301707" Y = "0.332979" T = "0" Pressure = "0" />
		<Point X = "0.2198153" Y = "0.3536974" T = "0" Pressure = "0" />
		<Point X = "0.2064176" Y = "0.3722236" T = "0" Pressure = "0" />
		<Point X = "0.188957" Y = "0.3873754" T = "0" Pressure = "0" />
		<Point X = "0.1698903" Y = "0.4004838" T = "0" Pressure = "0" />
		<Point X = "0.1500406" Y = "0.4124073" T = "0" Pressure = "0" />
		<Point X = "0.129573" Y = "0.4231189" T = "0" Pressure = "0" />
		<Point X = "0.1077322" Y = "0.4308302" T = "0" Pressure = "0" />
		<Point X = "0.08544257" Y = "0.4370492" T = "0" Pressure = "0" />
		<Point X = "0.0629715" Y = "0.4426649" T = "0" Pressure = "0" />
		<Point X = "0.04038005" Y = "0.4477019" T = "0" Pressure = "0" />
		<Point X = "0.01747465" Y = "0.4510791" T = "0" Pressure = "0" />
		<Point X = "-0.005560609" Y = "0.4535002" T = "0" Pressure = "0" />
		<Point X = "-0.02862989" Y = "0.4555604" T = "0" Pressure = "0" />
		<Point X = "-0.05177047" Y = "0.4560779" T = "0" Pressure = "0" />
		<Point X = "-0.07493262" Y = "0.4560779" T = "0" Pressure = "0" />
		<Point X = "-0.09809476" Y = "0.4560779" T = "0" Pressure = "0" />
		<Point X = "-0.1212569" Y = "0.4560779" T = "0" Pressure = "0" />
		<Point X = "-0.144419" Y = "0.4560779" T = "0" Pressure = "0" />
		<Point X = "-0.1675491" Y = "0.4555631" T = "0" Pressure = "0" />
		<Point X = "-0.190598" Y = "0.4540318" T = "0" Pressure = "0" />
		<Point X = "-0.2111166" Y = "0.4434848" T = "0" Pressure = "0" />
		<Point X = "-0.2267761" Y = "0.4272854" T = "0" Pressure = "0" />
	</Stroke>
</Gesture>
