<?xml version="1.0" encoding="utf-8" standalone="yes"?>
<Gesture Name = "U">
	<Stroke>
		<Point X = "-0.3153692" Y = "-0.6568242" T = "0" Pressure = "0" />
		<Point X = "-0.3205981" Y = "-0.630721" T = "0" Pressure = "0" />
		<Point X = "-0.3206107" Y = "-0.6041004" T = "0" Pressure = "0" />
		<Point X = "-0.3229813" Y = "-0.5776259" T = "0" Pressure = "0" />
		<Point X = "-0.3260256" Y = "-0.5511867" T = "0" Pressure = "0" />
		<Point X = "-0.3274263" Y = "-0.5246018" T = "0" Pressure = "0" />
		<Point X = "-0.3284592" Y = "-0.4980071" T = "0" Pressure = "0" />
		<Point X = "-0.3284592" Y = "-0.4713853" T = "0" Pressure = "0" />
		<Point X = "-0.3285796" Y = "-0.4447662" T = "0" Pressure = "0" />
		<Point X = "-0.3297895" Y = "-0.4181719" T = "0" Pressure = "0" />
		<Point X = "-0.3309995" Y = "-0.3915776" T = "0" Pressure = "0" />
		<Point X = "-0.33108" Y = "-0.3649576" T = "0" Pressure = "0" />
		<Point X = "-0.33108" Y = "-0.3383357" T = "0" Pressure = "0" />
		<Point X = "-0.33108" Y = "-0.3117139" T = "0" Pressure = "0" />
		<Point X = "-0.33108" Y = "-0.2850921" T = "0" Pressure = "0" />
		<Point X = "-0.33108" Y = "-0.2584702" T = "0" Pressure = "0" />
		<Point X = "-0.33108" Y = "-0.2318484" T = "0" Pressure = "0" />
		<Point X = "-0.33108" Y = "-0.2052266" T = "0" Pressure = "0" />
		<Point X = "-0.3301741" Y = "-0.1786209" T = "0" Pressure = "0" />
		<Point X = "-0.3292229" Y = "-0.1520161" T = "0" Pressure = "0" />
		<Point X = "-0.3284592" Y = "-0.1254079" T = "0" Pressure = "0" />
		<Point X = "-0.3284592" Y = "-0.09878612" T = "0" Pressure = "0" />
		<Point X = "-0.3284592" Y = "-0.0721643" T = "0" Pressure = "0" />
		<Point X = "-0.3284592" Y = "-0.04554247" T = "0" Pressure = "0" />
		<Point X = "-0.3284592" Y = "-0.01892064" T = "0" Pressure = "0" />
		<Point X = "-0.3284592" Y = "0.007701188" T = "0" Pressure = "0" />
		<Point X = "-0.3284592" Y = "0.03432302" T = "0" Pressure = "0" />
		<Point X = "-0.3284592" Y = "0.06094484" T = "0" Pressure = "0" />
		<Point X = "-0.3284592" Y = "0.08756667" T = "0" Pressure = "0" />
		<Point X = "-0.3284592" Y = "0.1141885" T = "0" Pressure = "0" />
		<Point X = "-0.3284592" Y = "0.1408103" T = "0" Pressure = "0" />
		<Point X = "-0.3242193" Y = "0.1670819" T = "0" Pressure = "0" />
		<Point X = "-0.3182346" Y = "0.1930069" T = "0" Pressure = "0" />
		<Point X = "-0.3114777" Y = "0.2187465" T = "0" Pressure = "0" />
		<Point X = "-0.3002605" Y = "0.2427159" T = "0" Pressure = "0" />
		<Point X = "-0.2816514" Y = "0.2617072" T = "0" Pressure = "0" />
		<Point X = "-0.2612236" Y = "0.2786378" T = "0" Pressure = "0" />
		<Point X = "-0.2380129" Y = "0.2915411" T = "0" Pressure = "0" />
		<Point X = "-0.2141998" Y = "0.3034432" T = "0" Pressure = "0" />
		<Point X = "-0.1896349" Y = "0.3135305" T = "0" Pressure = "0" />
		<Point X = "-0.1642858" Y = "0.3216467" T = "0" Pressure = "0" />
		<Point X = "-0.1386879" Y = "0.328959" T = "0" Pressure = "0" />
		<Point X = "-0.1124208" Y = "0.3330574" T = "0" Pressure = "0" />
		<Point X = "-0.08594847" Y = "0.3353135" T = "0" Pressure = "0" />
		<Point X = "-0.05932664" Y = "0.3353135" T = "0" Pressure = "0" />
		<Point X = "-0.03270481" Y = "0.3353135" T = "0" Pressure = "0" />
		<Point X = "-0.006082984" Y = "0.3353135" T = "0" Pressure = "0" />
		<Point X = "0.02053885" Y = "0.3353135" T = "0" Pressure = "0" />
		<Point X = "0.04716067" Y = "0.3353135" T = "0" Pressure = "0" />
		<Point X = "0.07372364" Y = "0.334601" T = "0" Pressure = "0" />
		<Point X = "0.09998449" Y = "0.3302319" T = "0" Pressure = "0" />
		<Point X = "0.1262943" Y = "0.3261685" T = "0" Pressure = "0" />
		<Point X = "0.1525715" Y = "0.3219014" T = "0" Pressure = "0" />
		<Point X = "0.1786245" Y = "0.3165325" T = "0" Pressure = "0" />
		<Point X = "0.2045232" Y = "0.3103952" T = "0" Pressure = "0" />
		<Point X = "0.2304091" Y = "0.3043512" T = "0" Pressure = "0" />
		<Point X = "0.2554888" Y = "0.2954519" T = "0" Pressure = "0" />
		<Point X = "0.2801021" Y = "0.2853173" T = "0" Pressure = "0" />
		<Point X = "0.3039831" Y = "0.2736465" T = "0" Pressure = "0" />
		<Point X = "0.3265369" Y = "0.2595493" T = "0" Pressure = "0" />
		<Point X = "0.3474682" Y = "0.2431151" T = "0" Pressure = "0" />
		<Point X = "0.365632" Y = "0.2236524" T = "0" Pressure = "0" />
		<Point X = "0.3837022" Y = "0.2041286" T = "0" Pressure = "0" />
		<Point X = "0.3941913" Y = "0.1796602" T = "0" Pressure = "0" />
		<Point X = "0.4032205" Y = "0.1546619" T = "0" Pressure = "0" />
		<Point X = "0.4108714" Y = "0.1291631" T = "0" Pressure = "0" />
		<Point X = "0.4171531" Y = "0.1033379" T = "0" Pressure = "0" />
		<Point X = "0.4218333" Y = "0.07713067" T = "0" Pressure = "0" />
		<Point X = "0.4265135" Y = "0.05092347" T = "0" Pressure = "0" />
		<Point X = "0.4317877" Y = "0.02483287" T = "0" Pressure = "0" />
		<Point X = "0.4373624" Y = "-0.001198731" T = "0" Pressure = "0" />
		<Point X = "0.4429371" Y = "-0.02723034" T = "0" Pressure = "0" />
		<Point X = "0.446324" Y = "-0.0536192" T = "0" Pressure = "0" />
		<Point X = "0.4493195" Y = "-0.08007195" T = "0" Pressure = "0" />
		<Point X = "0.4523152" Y = "-0.1065247" T = "0" Pressure = "0" />
		<Point X = "0.4553107" Y = "-0.1329775" T = "0" Pressure = "0" />
		<Point X = "0.4583063" Y = "-0.1594302" T = "0" Pressure = "0" />
		<Point X = "0.4605637" Y = "-0.1859494" T = "0" Pressure = "0" />
		<Point X = "0.4623364" Y = "-0.2125121" T = "0" Pressure = "0" />
		<Point X = "0.4641091" Y = "-0.2390748" T = "0" Pressure = "0" />
		<Point X = "0.4647351" Y = "-0.2656758" T = "0" Pressure = "0" />
		<Point X = "0.4647351" Y = "-0.2922976" T = "0" Pressure = "0" />
		<Point X = "0.4647351" Y = "-0.3189195" T = "0" Pressure = "0" />
		<Point X = "0.4651034" Y = "-0.3455362" T = "0" Pressure = "0" />
		<Point X = "0.4658396" Y = "-0.3721478" T = "0" Pressure = "0" />
		<Point X = "0.4665758" Y = "-0.3987595" T = "0" Pressure = "0" />
		<Point X = "0.467312" Y = "-0.4253711" T = "0" Pressure = "0" />
		<Point X = "0.4673421" Y = "-0.4519925" T = "0" Pressure = "0" />
		<Point X = "0.4673421" Y = "-0.4786144" T = "0" Pressure = "0" />
		<Point X = "0.4673421" Y = "-0.5052362" T = "0" Pressure = "0" />
		<Point X = "0.4667984" Y = "-0.531849" T = "0" Pressure = "0" />
		<Point X = "0.4659152" Y = "-0.5584561" T = "0" Pressure = "0" />
		<Point X = "0.465032" Y = "-0.5850633" T = "0" Pressure = "0" />
		<Point X = "0.4631333" Y = "-0.6116075" T = "0" Pressure = "0" />
		<Point X = "0.4607202" Y = "-0.6381198" T = "0" Pressure = "0" />
		<Point X = "0.4594936" Y = "-0.6646858" T = "0" Pressure = "0" />
	</Stroke>
</Gesture>
